fsm_tool/output/app_fsm/fsm.v
module fsm (
    input clk,
    input reset,
    input in_bit,
    output out_det
);
    reg [1:0] state;
    wire i_0 = in_bit;
    wire s_0 = state[0];
    wire s_1 = state[1];

    wire d_0 = ((~s_0) & s_1 & i_0);
    wire d_1 = (((~s_1) & (~i_0)) | ((~s_0) & (~i_0)));

    assign out_det = ((~s_0) & s_1 & i_0);

    always @(posedge clk or posedge reset) begin
        if (reset)
            state <= 2'b0;
        else begin
            state[0] <= d_0;
            state[1] <= d_1;
        end
    end
endmodule

fsm_tool/output/app_fsm/testbench.v
module fsm_tb;
    reg clk;
    reg reset;
    reg in_bit;
    wire out_det;
    fsm uut (
        .clk(clk),
        .reset(reset),
        .in_bit(in_bit),
        .out_det(out_det)
    );
    initial begin
        clk = 0;
        forever #5 clk = ~clk;
    end
    integer errors = 0;
    initial begin
        $dumpfile("testbench.vcd");
        $dumpvars(0, fsm_tb);
        reset = 1;
        in_bit = 0;
        #20;
        reset = 0;
        @(negedge clk);
        in_bit = 1'b1;
        #2;
        if (out_det !== 1'b0) begin
            $display("FAIL: out_det did not match expected 0. Got %b", out_det);
            errors = errors + 1;
        end
        @(negedge clk);
        in_bit = 1'b0;
        #2;
        if (out_det !== 1'b0) begin
            $display("FAIL: out_det did not match expected 0. Got %b", out_det);
            errors = errors + 1;
        end
        @(negedge clk);
        in_bit = 1'b1;
        #2;
        if (out_det !== 1'b1) begin
            $display("FAIL: out_det did not match expected 1. Got %b", out_det);
            errors = errors + 1;
        end
        @(negedge clk);
        in_bit = 1'b1;
        #2;
        if (out_det !== 1'b0) begin
            $display("FAIL: out_det did not match expected 0. Got %b", out_det);
            errors = errors + 1;
        end
        @(negedge clk);
        in_bit = 1'b1;
        #2;
        if (out_det !== 1'b0) begin
            $display("FAIL: out_det did not match expected 0. Got %b", out_det);
            errors = errors + 1;
        end
        @(negedge clk);
        in_bit = 1'b0;
        #2;
        if (out_det !== 1'b0) begin
            $display("FAIL: out_det did not match expected 0. Got %b", out_det);
            errors = errors + 1;
        end
        @(negedge clk);
        in_bit = 1'b0;
        #2;
        if (out_det !== 1'b0) begin
            $display("FAIL: out_det did not match expected 0. Got %b", out_det);
            errors = errors + 1;
        end
        @(negedge clk);
        in_bit = 1'b0;
        #2;
        if (out_det !== 1'b0) begin
            $display("FAIL: out_det did not match expected 0. Got %b", out_det);
            errors = errors + 1;
        end
        @(negedge clk);
        in_bit = 1'b0;
        #2;
        if (out_det !== 1'b0) begin
            $display("FAIL: out_det did not match expected 0. Got %b", out_det);
            errors = errors + 1;
        end
        @(negedge clk);
        in_bit = 1'b1;
        #2;
        if (out_det !== 1'b1) begin
            $display("FAIL: out_det did not match expected 1. Got %b", out_det);
            errors = errors + 1;
        end
        @(negedge clk);
        in_bit = 1'b0;
        #2;
        if (out_det !== 1'b0) begin
            $display("FAIL: out_det did not match expected 0. Got %b", out_det);
            errors = errors + 1;
        end
        @(negedge clk);
        in_bit = 1'b0;
        #2;
        if (out_det !== 1'b0) begin
            $display("FAIL: out_det did not match expected 0. Got %b", out_det);
            errors = errors + 1;
        end
        @(negedge clk);
        in_bit = 1'b0;
        #2;
        if (out_det !== 1'b0) begin
            $display("FAIL: out_det did not match expected 0. Got %b", out_det);
            errors = errors + 1;
        end
        @(negedge clk);
        in_bit = 1'b0;
        #2;
        if (out_det !== 1'b0) begin
            $display("FAIL: out_det did not match expected 0. Got %b", out_det);
            errors = errors + 1;
        end
        @(negedge clk);
        in_bit = 1'b1;
        #2;
        if (out_det !== 1'b1) begin
            $display("FAIL: out_det did not match expected 1. Got %b", out_det);
            errors = errors + 1;
        end
        @(negedge clk);
        in_bit = 1'b1;
        #2;
        if (out_det !== 1'b0) begin
            $display("FAIL: out_det did not match expected 0. Got %b", out_det);
            errors = errors + 1;
        end
        @(negedge clk);
        in_bit = 1'b1;
        #2;
        if (out_det !== 1'b0) begin
            $display("FAIL: out_det did not match expected 0. Got %b", out_det);
            errors = errors + 1;
        end
        @(negedge clk);
        in_bit = 1'b0;
        #2;
        if (out_det !== 1'b0) begin
            $display("FAIL: out_det did not match expected 0. Got %b", out_det);
            errors = errors + 1;
        end
        @(negedge clk);
        in_bit = 1'b1;
        #2;
        if (out_det !== 1'b1) begin
            $display("FAIL: out_det did not match expected 1. Got %b", out_det);
            errors = errors + 1;
        end
        @(negedge clk);
        in_bit = 1'b0;
        #2;
        if (out_det !== 1'b0) begin
            $display("FAIL: out_det did not match expected 0. Got %b", out_det);
            errors = errors + 1;
        end
        @(negedge clk);
        in_bit = 1'b1;
        #2;
        if (out_det !== 1'b1) begin
            $display("FAIL: out_det did not match expected 1. Got %b", out_det);
            errors = errors + 1;
        end
        @(negedge clk);
        in_bit = 1'b0;
        #2;
        if (out_det !== 1'b0) begin
            $display("FAIL: out_det did not match expected 0. Got %b", out_det);
            errors = errors + 1;
        end
        @(negedge clk);
        in_bit = 1'b0;
        #2;
        if (out_det !== 1'b0) begin
            $display("FAIL: out_det did not match expected 0. Got %b", out_det);
            errors = errors + 1;
        end
        @(negedge clk);
        in_bit = 1'b0;
        #2;
        if (out_det !== 1'b0) begin
            $display("FAIL: out_det did not match expected 0. Got %b", out_det);
            errors = errors + 1;
        end
        @(negedge clk);
        in_bit = 1'b0;
        #2;
        if (out_det !== 1'b0) begin
            $display("FAIL: out_det did not match expected 0. Got %b", out_det);
            errors = errors + 1;
        end
        @(negedge clk);
        in_bit = 1'b1;
        #2;
        if (out_det !== 1'b1) begin
            $display("FAIL: out_det did not match expected 1. Got %b", out_det);
            errors = errors + 1;
        end
        @(negedge clk);
        in_bit = 1'b1;
        #2;
        if (out_det !== 1'b0) begin
            $display("FAIL: out_det did not match expected 0. Got %b", out_det);
            errors = errors + 1;
        end
        @(negedge clk);
        in_bit = 1'b0;
        #2;
        if (out_det !== 1'b0) begin
            $display("FAIL: out_det did not match expected 0. Got %b", out_det);
            errors = errors + 1;
        end
        @(negedge clk);
        in_bit = 1'b0;
        #2;
        if (out_det !== 1'b0) begin
            $display("FAIL: out_det did not match expected 0. Got %b", out_det);
            errors = errors + 1;
        end
        @(negedge clk);
        in_bit = 1'b1;
        #2;
        if (out_det !== 1'b1) begin
            $display("FAIL: out_det did not match expected 1. Got %b", out_det);
            errors = errors + 1;
        end
        @(negedge clk);
        in_bit = 1'b1;
        #2;
        if (out_det !== 1'b0) begin
            $display("FAIL: out_det did not match expected 0. Got %b", out_det);
            errors = errors + 1;
        end
        @(negedge clk);
        in_bit = 1'b1;
        #2;
        if (out_det !== 1'b0) begin
            $display("FAIL: out_det did not match expected 0. Got %b", out_det);
            errors = errors + 1;
        end
        @(negedge clk);
        in_bit = 1'b1;
        #2;
        if (out_det !== 1'b0) begin
            $display("FAIL: out_det did not match expected 0. Got %b", out_det);
            errors = errors + 1;
        end
        @(negedge clk);
        in_bit = 1'b1;
        #2;
        if (out_det !== 1'b0) begin
            $display("FAIL: out_det did not match expected 0. Got %b", out_det);
            errors = errors + 1;
        end
        @(negedge clk);
        in_bit = 1'b0;
        #2;
        if (out_det !== 1'b0) begin
            $display("FAIL: out_det did not match expected 0. Got %b", out_det);
            errors = errors + 1;
        end
        @(negedge clk);
        in_bit = 1'b0;
        #2;
        if (out_det !== 1'b0) begin
            $display("FAIL: out_det did not match expected 0. Got %b", out_det);
            errors = errors + 1;
        end
        @(negedge clk);
        in_bit = 1'b0;
        #2;
        if (out_det !== 1'b0) begin
            $display("FAIL: out_det did not match expected 0. Got %b", out_det);
            errors = errors + 1;
        end
        @(negedge clk);
        in_bit = 1'b1;
        #2;
        if (out_det !== 1'b1) begin
            $display("FAIL: out_det did not match expected 1. Got %b", out_det);
            errors = errors + 1;
        end
        @(negedge clk);
        in_bit = 1'b0;
        #2;
        if (out_det !== 1'b0) begin
            $display("FAIL: out_det did not match expected 0. Got %b", out_det);
            errors = errors + 1;
        end
        @(negedge clk);
        in_bit = 1'b0;
        #2;
        if (out_det !== 1'b0) begin
            $display("FAIL: out_det did not match expected 0. Got %b", out_det);
            errors = errors + 1;
        end
        @(negedge clk);
        in_bit = 1'b0;
        #2;
        if (out_det !== 1'b0) begin
            $display("FAIL: out_det did not match expected 0. Got %b", out_det);
            errors = errors + 1;
        end
        @(negedge clk);
        in_bit = 1'b0;
        #2;
        if (out_det !== 1'b0) begin
            $display("FAIL: out_det did not match expected 0. Got %b", out_det);
            errors = errors + 1;
        end
        @(negedge clk);
        in_bit = 1'b0;
        #2;
        if (out_det !== 1'b0) begin
            $display("FAIL: out_det did not match expected 0. Got %b", out_det);
            errors = errors + 1;
        end
        @(negedge clk);
        in_bit = 1'b0;
        #2;
        if (out_det !== 1'b0) begin
            $display("FAIL: out_det did not match expected 0. Got %b", out_det);
            errors = errors + 1;
        end
        @(negedge clk);
        in_bit = 1'b0;
        #2;
        if (out_det !== 1'b0) begin
            $display("FAIL: out_det did not match expected 0. Got %b", out_det);
            errors = errors + 1;
        end
        @(negedge clk);
        in_bit = 1'b1;
        #2;
        if (out_det !== 1'b1) begin
            $display("FAIL: out_det did not match expected 1. Got %b", out_det);
            errors = errors + 1;
        end
        @(negedge clk);
        in_bit = 1'b1;
        #2;
        if (out_det !== 1'b0) begin
            $display("FAIL: out_det did not match expected 0. Got %b", out_det);
            errors = errors + 1;
        end
        @(negedge clk);
        in_bit = 1'b1;
        #2;
        if (out_det !== 1'b0) begin
            $display("FAIL: out_det did not match expected 0. Got %b", out_det);
            errors = errors + 1;
        end
        @(negedge clk);
        in_bit = 1'b0;
        #2;
        if (out_det !== 1'b0) begin
            $display("FAIL: out_det did not match expected 0. Got %b", out_det);
            errors = errors + 1;
        end
        @(negedge clk);
        in_bit = 1'b1;
        #2;
        if (out_det !== 1'b1) begin
            $display("FAIL: out_det did not match expected 1. Got %b", out_det);
            errors = errors + 1;
        end
        @(negedge clk);
        if (errors == 0) begin
            $display("PASS");
        end else begin
            $display("FAIL (with %d errors)", errors);
        end
        $finish;
    end
endmodule

fsm_tool/output/app_fsm/testbench.vcd
$date
	Fri Apr 24 11:22:29 2026
$end
$version
	Icarus Verilog
$end
$timescale
	1s
$end
$scope module fsm_tb $end
$var wire 1 ! out_det $end
$var reg 1 " clk $end
$var reg 1 # in_bit $end
$var reg 1 $ reset $end
$var integer 32 % errors [31:0] $end
$scope module uut $end
$var wire 1 " clk $end
$var wire 1 & d_0 $end
$var wire 1 ' d_1 $end
$var wire 1 ( i_0 $end
$var wire 1 # in_bit $end
$var wire 1 ! out_det $end
$var wire 1 $ reset $end
$var wire 1 ) s_1 $end
$var wire 1 * s_0 $end
$var reg 2 + state [1:0] $end
$upscope $end
$upscope $end
$enddefinitions $end
$comment Show the parameter values. $end
$dumpall
$end
#0
$dumpvars
b0 +
0*
0)
0(
1'
0&
b0 %
1$
0#
0"
0!
$end
#5
1"
#10
0"
#15
1"
#20
0'
1(
1#
0"
0$
#25
1"
#30
1'
0(
0#
0"
#35
1)
b10 +
1"
#40
0'
1&
1!
1(
1#
0"
#45
0!
0&
0)
1*
b1 +
1"
#50
0"
#55
0*
b0 +
1"
#60
0"
#65
1"
#70
1'
0(
0#
0"
#75
1)
b10 +
1"
#80
0"
#85
1"
#90
0"
#95
1"
#100
0"
#105
1"
#110
0'
1&
1!
1(
1#
0"
#115
0!
0&
0)
1*
b1 +
1"
#120
1'
0(
0#
0"
#125
1)
0*
b10 +
1"
#130
0"
#135
1"
#140
0"
#145
1"
#150
0"
#155
1"
#160
0'
1&
1!
1(
1#
0"
#165
0!
0&
0)
1*
b1 +
1"
#170
0"
#175
0*
b0 +
1"
#180
0"
#185
1"
#190
1'
0(
0#
0"
#195
1)
b10 +
1"
#200
0'
1&
1!
1(
1#
0"
#205
0!
0&
0)
1*
b1 +
1"
#210
1'
0(
0#
0"
#215
1)
0*
b10 +
1"
#220
0'
1&
1!
1(
1#
0"
#225
0!
0&
0)
1*
b1 +
1"
#230
1'
0(
0#
0"
#235
1)
0*
b10 +
1"
#240
0"
#245
1"
#250
0"
#255
1"
#260
0"
#265
1"
#270
0'
1&
1!
1(
1#
0"
#275
0!
0&
0)
1*
b1 +
1"
#280
0"
#285
0*
b0 +
1"
#290
1'
0(
0#
0"
#295
1)
b10 +
1"
#300
0"
#305
1"
#310
0'
1&
1!
1(
1#
0"
#315
0!
0&
0)
1*
b1 +
1"
#320
0"
#325
0*
b0 +
1"
#330
0"
#335
1"
#340
0"
#345
1"
#350
0"
#355
1"
#360
1'
0(
0#
0"
#365
1)
b10 +
1"
#370
0"
#375
1"
#380
0"
#385
1"
#390
0'
1&
1!
1(
1#
0"
#395
0!
0&
0)
1*
b1 +
1"
#400
1'
0(
0#
0"
#405
1)
0*
b10 +
1"
#410
0"
#415
1"
#420
0"
#425
1"
#430
0"
#435
1"
#440
0"
#445
1"
#450
0"
#455
1"
#460
0"
#465
1"
#470
0'
1&
1!
1(
1#
0"
#475
0!
0&
0)
1*
b1 +
1"
#480
0"
#485
0*
b0 +
1"
#490
0"
#495
1"
#500
1'
0(
0#
0"
#505
1)
b10 +
1"
#510
0'
1&
1!
1(
1#
0"
#515
0!
0&
0)
1*
b1 +
1"
