fsm_tool/output/test4/fsm.v
module fsm (
    input clk,
    input reset,
    input en,
    output q1,
    output q0
);
    reg [1:0] state;
    wire i_0 = en;
    wire s_0 = state[0];
    wire s_1 = state[1];

    wire d_0 = ((s_0 & (~s_1)) | (s_0 & (~i_0)) | ((~s_0) & s_1 & i_0));
    wire d_1 = (((~s_1) & i_0) | (s_1 & (~i_0)));

    assign q1 = ((s_0 & (~s_1)) | (s_0 & (~i_0)) | ((~s_0) & s_1 & i_0));
    assign q0 = (((~s_1) & i_0) | (s_1 & (~i_0)));

    always @(posedge clk or posedge reset) begin
        if (reset)
            state <= 2'b0;
        else begin
            state[0] <= d_0;
            state[1] <= d_1;
        end
    end
endmodule

output/test4/testbench.v
module fsm_tb;
    reg clk;
    reg reset;
    reg en;
    wire q1;
    wire q0;
    fsm uut (
        .clk(clk),
        .reset(reset),
        .en(en),
        .q1(q1),
        .q0(q0)
    );
    initial begin
        clk = 0;
        forever #5 clk = ~clk;
    end
    integer errors = 0;
    initial begin
        $dumpfile("testbench.vcd");
        $dumpvars(0, fsm_tb);
        reset = 1;
        en = 0;
        #20;
        reset = 0;
        @(negedge clk);
        en = 1'b1;
        #2;
        if (q1 !== 1'b0) begin
            $display("FAIL: q1 did not match expected 0. Got %b", q1);
            errors = errors + 1;
        end
        if (q0 !== 1'b1) begin
            $display("FAIL: q0 did not match expected 1. Got %b", q0);
            errors = errors + 1;
        end
        @(negedge clk);
        en = 1'b1;
        #2;
        if (q1 !== 1'b1) begin
            $display("FAIL: q1 did not match expected 1. Got %b", q1);
            errors = errors + 1;
        end
        if (q0 !== 1'b0) begin
            $display("FAIL: q0 did not match expected 0. Got %b", q0);
            errors = errors + 1;
        end
        @(negedge clk);
        en = 1'b0;
        #2;
        if (q1 !== 1'b1) begin
            $display("FAIL: q1 did not match expected 1. Got %b", q1);
            errors = errors + 1;
        end
        if (q0 !== 1'b0) begin
            $display("FAIL: q0 did not match expected 0. Got %b", q0);
            errors = errors + 1;
        end
        @(negedge clk);
        en = 1'b0;
        #2;
        if (q1 !== 1'b1) begin
            $display("FAIL: q1 did not match expected 1. Got %b", q1);
            errors = errors + 1;
        end
        if (q0 !== 1'b0) begin
            $display("FAIL: q0 did not match expected 0. Got %b", q0);
            errors = errors + 1;
        end
        @(negedge clk);
        en = 1'b1;
        #2;
        if (q1 !== 1'b1) begin
            $display("FAIL: q1 did not match expected 1. Got %b", q1);
            errors = errors + 1;
        end
        if (q0 !== 1'b1) begin
            $display("FAIL: q0 did not match expected 1. Got %b", q0);
            errors = errors + 1;
        end
        @(negedge clk);
        en = 1'b0;
        #2;
        if (q1 !== 1'b1) begin
            $display("FAIL: q1 did not match expected 1. Got %b", q1);
            errors = errors + 1;
        end
        if (q0 !== 1'b1) begin
            $display("FAIL: q0 did not match expected 1. Got %b", q0);
            errors = errors + 1;
        end
        @(negedge clk);
        en = 1'b1;
        #2;
        if (q1 !== 1'b0) begin
            $display("FAIL: q1 did not match expected 0. Got %b", q1);
            errors = errors + 1;
        end
        if (q0 !== 1'b0) begin
            $display("FAIL: q0 did not match expected 0. Got %b", q0);
            errors = errors + 1;
        end
        @(negedge clk);
        en = 1'b0;
        #2;
        if (q1 !== 1'b0) begin
            $display("FAIL: q1 did not match expected 0. Got %b", q1);
            errors = errors + 1;
        end
        if (q0 !== 1'b0) begin
            $display("FAIL: q0 did not match expected 0. Got %b", q0);
            errors = errors + 1;
        end
        @(negedge clk);
        en = 1'b1;
        #2;
        if (q1 !== 1'b0) begin
            $display("FAIL: q1 did not match expected 0. Got %b", q1);
            errors = errors + 1;
        end
        if (q0 !== 1'b1) begin
            $display("FAIL: q0 did not match expected 1. Got %b", q0);
            errors = errors + 1;
        end
        @(negedge clk);
        en = 1'b0;
        #2;
        if (q1 !== 1'b0) begin
            $display("FAIL: q1 did not match expected 0. Got %b", q1);
            errors = errors + 1;
        end
        if (q0 !== 1'b1) begin
            $display("FAIL: q0 did not match expected 1. Got %b", q0);
            errors = errors + 1;
        end
        @(negedge clk);
        en = 1'b0;
        #2;
        if (q1 !== 1'b0) begin
            $display("FAIL: q1 did not match expected 0. Got %b", q1);
            errors = errors + 1;
        end
        if (q0 !== 1'b1) begin
            $display("FAIL: q0 did not match expected 1. Got %b", q0);
            errors = errors + 1;
        end
        @(negedge clk);
        en = 1'b0;
        #2;
        if (q1 !== 1'b0) begin
            $display("FAIL: q1 did not match expected 0. Got %b", q1);
            errors = errors + 1;
        end
        if (q0 !== 1'b1) begin
            $display("FAIL: q0 did not match expected 1. Got %b", q0);
            errors = errors + 1;
        end
        @(negedge clk);
        en = 1'b0;
        #2;
        if (q1 !== 1'b0) begin
            $display("FAIL: q1 did not match expected 0. Got %b", q1);
            errors = errors + 1;
        end
        if (q0 !== 1'b1) begin
            $display("FAIL: q0 did not match expected 1. Got %b", q0);
            errors = errors + 1;
        end
        @(negedge clk);
        en = 1'b0;
        #2;
        if (q1 !== 1'b0) begin
            $display("FAIL: q1 did not match expected 0. Got %b", q1);
            errors = errors + 1;
        end
        if (q0 !== 1'b1) begin
            $display("FAIL: q0 did not match expected 1. Got %b", q0);
            errors = errors + 1;
        end
        @(negedge clk);
        en = 1'b1;
        #2;
        if (q1 !== 1'b1) begin
            $display("FAIL: q1 did not match expected 1. Got %b", q1);
            errors = errors + 1;
        end
        if (q0 !== 1'b0) begin
            $display("FAIL: q0 did not match expected 0. Got %b", q0);
            errors = errors + 1;
        end
        @(negedge clk);
        en = 1'b1;
        #2;
        if (q1 !== 1'b1) begin
            $display("FAIL: q1 did not match expected 1. Got %b", q1);
            errors = errors + 1;
        end
        if (q0 !== 1'b1) begin
            $display("FAIL: q0 did not match expected 1. Got %b", q0);
            errors = errors + 1;
        end
        @(negedge clk);
        en = 1'b1;
        #2;
        if (q1 !== 1'b0) begin
            $display("FAIL: q1 did not match expected 0. Got %b", q1);
            errors = errors + 1;
        end
        if (q0 !== 1'b0) begin
            $display("FAIL: q0 did not match expected 0. Got %b", q0);
            errors = errors + 1;
        end
        @(negedge clk);
        en = 1'b1;
        #2;
        if (q1 !== 1'b0) begin
            $display("FAIL: q1 did not match expected 0. Got %b", q1);
            errors = errors + 1;
        end
        if (q0 !== 1'b1) begin
            $display("FAIL: q0 did not match expected 1. Got %b", q0);
            errors = errors + 1;
        end
        @(negedge clk);
        en = 1'b0;
        #2;
        if (q1 !== 1'b0) begin
            $display("FAIL: q1 did not match expected 0. Got %b", q1);
            errors = errors + 1;
        end
        if (q0 !== 1'b1) begin
            $display("FAIL: q0 did not match expected 1. Got %b", q0);
            errors = errors + 1;
        end
        @(negedge clk);
        en = 1'b0;
        #2;
        if (q1 !== 1'b0) begin
            $display("FAIL: q1 did not match expected 0. Got %b", q1);
            errors = errors + 1;
        end
        if (q0 !== 1'b1) begin
            $display("FAIL: q0 did not match expected 1. Got %b", q0);
            errors = errors + 1;
        end
        @(negedge clk);
        en = 1'b0;
        #2;
        if (q1 !== 1'b0) begin
            $display("FAIL: q1 did not match expected 0. Got %b", q1);
            errors = errors + 1;
        end
        if (q0 !== 1'b1) begin
            $display("FAIL: q0 did not match expected 1. Got %b", q0);
            errors = errors + 1;
        end
        @(negedge clk);
        en = 1'b0;
        #2;
        if (q1 !== 1'b0) begin
            $display("FAIL: q1 did not match expected 0. Got %b", q1);
            errors = errors + 1;
        end
        if (q0 !== 1'b1) begin
            $display("FAIL: q0 did not match expected 1. Got %b", q0);
            errors = errors + 1;
        end
        @(negedge clk);
        en = 1'b1;
        #2;
        if (q1 !== 1'b1) begin
            $display("FAIL: q1 did not match expected 1. Got %b", q1);
            errors = errors + 1;
        end
        if (q0 !== 1'b0) begin
            $display("FAIL: q0 did not match expected 0. Got %b", q0);
            errors = errors + 1;
        end
        @(negedge clk);
        en = 1'b0;
        #2;
        if (q1 !== 1'b1) begin
            $display("FAIL: q1 did not match expected 1. Got %b", q1);
            errors = errors + 1;
        end
        if (q0 !== 1'b0) begin
            $display("FAIL: q0 did not match expected 0. Got %b", q0);
            errors = errors + 1;
        end
        @(negedge clk);
        en = 1'b0;
        #2;
        if (q1 !== 1'b1) begin
            $display("FAIL: q1 did not match expected 1. Got %b", q1);
            errors = errors + 1;
        end
        if (q0 !== 1'b0) begin
            $display("FAIL: q0 did not match expected 0. Got %b", q0);
            errors = errors + 1;
        end
        @(negedge clk);
        en = 1'b0;
        #2;
        if (q1 !== 1'b1) begin
            $display("FAIL: q1 did not match expected 1. Got %b", q1);
            errors = errors + 1;
        end
        if (q0 !== 1'b0) begin
            $display("FAIL: q0 did not match expected 0. Got %b", q0);
            errors = errors + 1;
        end
        @(negedge clk);
        en = 1'b0;
        #2;
        if (q1 !== 1'b1) begin
            $display("FAIL: q1 did not match expected 1. Got %b", q1);
            errors = errors + 1;
        end
        if (q0 !== 1'b0) begin
            $display("FAIL: q0 did not match expected 0. Got %b", q0);
            errors = errors + 1;
        end
        @(negedge clk);
        en = 1'b1;
        #2;
        if (q1 !== 1'b1) begin
            $display("FAIL: q1 did not match expected 1. Got %b", q1);
            errors = errors + 1;
        end
        if (q0 !== 1'b1) begin
            $display("FAIL: q0 did not match expected 1. Got %b", q0);
            errors = errors + 1;
        end
        @(negedge clk);
        en = 1'b0;
        #2;
        if (q1 !== 1'b1) begin
            $display("FAIL: q1 did not match expected 1. Got %b", q1);
            errors = errors + 1;
        end
        if (q0 !== 1'b1) begin
            $display("FAIL: q0 did not match expected 1. Got %b", q0);
            errors = errors + 1;
        end
        @(negedge clk);
        en = 1'b0;
        #2;
        if (q1 !== 1'b1) begin
            $display("FAIL: q1 did not match expected 1. Got %b", q1);
            errors = errors + 1;
        end
        if (q0 !== 1'b1) begin
            $display("FAIL: q0 did not match expected 1. Got %b", q0);
            errors = errors + 1;
        end
        @(negedge clk);
        en = 1'b1;
        #2;
        if (q1 !== 1'b0) begin
            $display("FAIL: q1 did not match expected 0. Got %b", q1);
            errors = errors + 1;
        end
        if (q0 !== 1'b0) begin
            $display("FAIL: q0 did not match expected 0. Got %b", q0);
            errors = errors + 1;
        end
        @(negedge clk);
        en = 1'b1;
        #2;
        if (q1 !== 1'b0) begin
            $display("FAIL: q1 did not match expected 0. Got %b", q1);
            errors = errors + 1;
        end
        if (q0 !== 1'b1) begin
            $display("FAIL: q0 did not match expected 1. Got %b", q0);
            errors = errors + 1;
        end
        @(negedge clk);
        en = 1'b0;
        #2;
        if (q1 !== 1'b0) begin
            $display("FAIL: q1 did not match expected 0. Got %b", q1);
            errors = errors + 1;
        end
        if (q0 !== 1'b1) begin
            $display("FAIL: q0 did not match expected 1. Got %b", q0);
            errors = errors + 1;
        end
        @(negedge clk);
        en = 1'b1;
        #2;
        if (q1 !== 1'b1) begin
            $display("FAIL: q1 did not match expected 1. Got %b", q1);
            errors = errors + 1;
        end
        if (q0 !== 1'b0) begin
            $display("FAIL: q0 did not match expected 0. Got %b", q0);
            errors = errors + 1;
        end
        @(negedge clk);
        en = 1'b0;
        #2;
        if (q1 !== 1'b1) begin
            $display("FAIL: q1 did not match expected 1. Got %b", q1);
            errors = errors + 1;
        end
        if (q0 !== 1'b0) begin
            $display("FAIL: q0 did not match expected 0. Got %b", q0);
            errors = errors + 1;
        end
        @(negedge clk);
        en = 1'b1;
        #2;
        if (q1 !== 1'b1) begin
            $display("FAIL: q1 did not match expected 1. Got %b", q1);
            errors = errors + 1;
        end
        if (q0 !== 1'b1) begin
            $display("FAIL: q0 did not match expected 1. Got %b", q0);
            errors = errors + 1;
        end
        @(negedge clk);
        en = 1'b1;
        #2;
        if (q1 !== 1'b0) begin
            $display("FAIL: q1 did not match expected 0. Got %b", q1);
            errors = errors + 1;
        end
        if (q0 !== 1'b0) begin
            $display("FAIL: q0 did not match expected 0. Got %b", q0);
            errors = errors + 1;
        end
        @(negedge clk);
        en = 1'b0;
        #2;
        if (q1 !== 1'b0) begin
            $display("FAIL: q1 did not match expected 0. Got %b", q1);
            errors = errors + 1;
        end
        if (q0 !== 1'b0) begin
            $display("FAIL: q0 did not match expected 0. Got %b", q0);
            errors = errors + 1;
        end
        @(negedge clk);
        en = 1'b1;
        #2;
        if (q1 !== 1'b0) begin
            $display("FAIL: q1 did not match expected 0. Got %b", q1);
            errors = errors + 1;
        end
        if (q0 !== 1'b1) begin
            $display("FAIL: q0 did not match expected 1. Got %b", q0);
            errors = errors + 1;
        end
        @(negedge clk);
        en = 1'b1;
        #2;
        if (q1 !== 1'b1) begin
            $display("FAIL: q1 did not match expected 1. Got %b", q1);
            errors = errors + 1;
        end
        if (q0 !== 1'b0) begin
            $display("FAIL: q0 did not match expected 0. Got %b", q0);
            errors = errors + 1;
        end
        @(negedge clk);
        en = 1'b1;
        #2;
        if (q1 !== 1'b1) begin
            $display("FAIL: q1 did not match expected 1. Got %b", q1);
            errors = errors + 1;
        end
        if (q0 !== 1'b1) begin
            $display("FAIL: q0 did not match expected 1. Got %b", q0);
            errors = errors + 1;
        end
        @(negedge clk);
        en = 1'b1;
        #2;
        if (q1 !== 1'b0) begin
            $display("FAIL: q1 did not match expected 0. Got %b", q1);
            errors = errors + 1;
        end
        if (q0 !== 1'b0) begin
            $display("FAIL: q0 did not match expected 0. Got %b", q0);
            errors = errors + 1;
        end
        @(negedge clk);
        en = 1'b1;
        #2;
        if (q1 !== 1'b0) begin
            $display("FAIL: q1 did not match expected 0. Got %b", q1);
            errors = errors + 1;
        end
        if (q0 !== 1'b1) begin
            $display("FAIL: q0 did not match expected 1. Got %b", q0);
            errors = errors + 1;
        end
        @(negedge clk);
        en = 1'b0;
        #2;
        if (q1 !== 1'b0) begin
            $display("FAIL: q1 did not match expected 0. Got %b", q1);
            errors = errors + 1;
        end
        if (q0 !== 1'b1) begin
            $display("FAIL: q0 did not match expected 1. Got %b", q0);
            errors = errors + 1;
        end
        @(negedge clk);
        en = 1'b0;
        #2;
        if (q1 !== 1'b0) begin
            $display("FAIL: q1 did not match expected 0. Got %b", q1);
            errors = errors + 1;
        end
        if (q0 !== 1'b1) begin
            $display("FAIL: q0 did not match expected 1. Got %b", q0);
            errors = errors + 1;
        end
        @(negedge clk);
        en = 1'b1;
        #2;
        if (q1 !== 1'b1) begin
            $display("FAIL: q1 did not match expected 1. Got %b", q1);
            errors = errors + 1;
        end
        if (q0 !== 1'b0) begin
            $display("FAIL: q0 did not match expected 0. Got %b", q0);
            errors = errors + 1;
        end
        @(negedge clk);
        en = 1'b1;
        #2;
        if (q1 !== 1'b1) begin
            $display("FAIL: q1 did not match expected 1. Got %b", q1);
            errors = errors + 1;
        end
        if (q0 !== 1'b1) begin
            $display("FAIL: q0 did not match expected 1. Got %b", q0);
            errors = errors + 1;
        end
        @(negedge clk);
        en = 1'b1;
        #2;
        if (q1 !== 1'b0) begin
            $display("FAIL: q1 did not match expected 0. Got %b", q1);
            errors = errors + 1;
        end
        if (q0 !== 1'b0) begin
            $display("FAIL: q0 did not match expected 0. Got %b", q0);
            errors = errors + 1;
        end
        @(negedge clk);
        en = 1'b0;
        #2;
        if (q1 !== 1'b0) begin
            $display("FAIL: q1 did not match expected 0. Got %b", q1);
            errors = errors + 1;
        end
        if (q0 !== 1'b0) begin
            $display("FAIL: q0 did not match expected 0. Got %b", q0);
            errors = errors + 1;
        end
        @(negedge clk);
        en = 1'b1;
        #2;
        if (q1 !== 1'b0) begin
            $display("FAIL: q1 did not match expected 0. Got %b", q1);
            errors = errors + 1;
        end
        if (q0 !== 1'b1) begin
            $display("FAIL: q0 did not match expected 1. Got %b", q0);
            errors = errors + 1;
        end
        @(negedge clk);
        if (errors == 0) begin
            $display("PASS");
        end else begin
            $display("FAIL (with %d errors)", errors);
        end
        $finish;
    end
endmodule

fsm_tool/output/test4/testbench.vcd
$date
	Wed Apr 22 15:19:15 2026
$end
$version
	Icarus Verilog
$end
$timescale
	1s
$end
$scope module fsm_tb $end
$var wire 1 ! q1 $end
$var wire 1 " q0 $end
$var reg 1 # clk $end
$var reg 1 $ en $end
$var reg 1 % reset $end
$var integer 32 & errors [31:0] $end
$scope module uut $end
$var wire 1 # clk $end
$var wire 1 ' d_0 $end
$var wire 1 ( d_1 $end
$var wire 1 $ en $end
$var wire 1 ) i_0 $end
$var wire 1 " q0 $end
$var wire 1 ! q1 $end
$var wire 1 % reset $end
$var wire 1 * s_1 $end
$var wire 1 + s_0 $end
$var reg 2 , state [1:0] $end
$upscope $end
$upscope $end
$enddefinitions $end
$comment Show the parameter values. $end
$dumpall
$end
#0
$dumpvars
b0 ,
0+
0*
0)
0(
0'
b0 &
1%
0$
0#
0"
0!
$end
#5
1#
#10
0#
#15
1#
#20
1(
1"
1)
1$
0#
0%
#25
0"
1!
0(
1'
1*
b10 ,
1#
#30
0#
#35
1"
1(
0*
1+
b1 ,
1#
#40
0(
0"
0)
0$
0#
#45
1#
#50
0#
#55
1#
#60
1(
1"
1)
1$
0#
#65
0!
0'
0"
0(
1*
b11 ,
1#
#70
1'
1!
1(
1"
0)
0$
0#
#75
1#
#80
0'
0!
0(
0"
1)
1$
0#
#85
1"
1(
0*
0+
b0 ,
1#
#90
0(
0"
0)
0$
0#
#95
1#
#100
1(
1"
1)
1$
0#
#105
0"
1!
0(
1'
1*
b10 ,
1#
#110
1(
1"
0'
0!
0)
0$
0#
#115
1#
#120
0#
#125
1#
#130
0#
#135
1#
#140
0#
#145
1#
#150
0#
#155
1#
#160
0(
0"
1'
1!
1)
1$
0#
#165
1"
1(
0*
1+
b1 ,
1#
#170
0#
#175
0!
0'
0"
0(
1*
b11 ,
1#
#180
0#
#185
1"
1(
0*
0+
b0 ,
1#
#190
0#
#195
0"
1!
0(
1'
1*
b10 ,
1#
#200
1(
1"
0'
0!
0)
0$
0#
#205
1#
#210
0#
#215
1#
#220
0#
#225
1#
#230
0#
#235
1#
#240
0(
0"
1'
1!
1)
1$
0#
#245
1"
1(
0*
1+
b1 ,
1#
#250
0(
0"
0)
0$
0#
#255
1#
#260
0#
#265
1#
#270
0#
#275
1#
#280
0#
#285
1#
#290
1(
1"
1)
1$
0#
#295
0!
0'
0"
0(
1*
b11 ,
1#
#300
1'
1!
1(
1"
0)
0$
0#
#305
1#
#310
0#
#315
1#
#320
0'
0!
0(
0"
1)
1$
0#
#325
1"
1(
0*
0+
b0 ,
1#
#330
0#
#335
0"
1!
0(
1'
1*
b10 ,
1#
#340
1(
1"
0'
0!
0)
0$
0#
#345
1#
#350
0(
0"
1'
1!
1)
1$
0#
#355
1"
1(
0*
1+
b1 ,
1#
#360
0(
0"
0)
0$
0#
#365
1#
#370
1(
1"
1)
1$
0#
#375
0!
0'
0"
0(
1*
b11 ,
1#
#380
0#
#385
1"
1(
0*
0+
b0 ,
1#
#390
0(
0"
0)
0$
0#
#395
1#
#400
1(
1"
1)
1$
0#
#405
0"
1!
0(
1'
1*
b10 ,
1#
#410
0#
#415
1"
1(
0*
1+
b1 ,
1#
#420
0#
#425
0!
0'
0"
0(
1*
b11 ,
1#
#430
0#
#435
1"
1(
0*
0+
b0 ,
1#
#440
0#
#445
0"
1!
0(
1'
1*
b10 ,
1#
#450
1(
1"
0'
0!
0)
0$
0#
#455
1#
#460
0#
#465
1#
#470
0(
0"
1'
1!
1)
1$
0#
#475
1"
1(
0*
1+
b1 ,
1#
#480
0#
#485
0!
0'
0"
0(
1*
b11 ,
1#
#490
0#
#495
1"
1(
0*
0+
b0 ,
1#
#500
0(
0"
0)
0$
0#
#505
1#
#510
1(
1"
1)
1$
0#
#515
0"
1!
0(
1'
1*
b10 ,
1#
